MANIFEST.in
README.txt
setup.cfg
setup.py
Products/__init__.py
Products.Zpydoc.egg-info/PKG-INFO
Products.Zpydoc.egg-info/SOURCES.txt
Products.Zpydoc.egg-info/dependency_links.txt
Products.Zpydoc.egg-info/entry_points.txt
Products.Zpydoc.egg-info/namespace_packages.txt
Products.Zpydoc.egg-info/not-zip-safe
Products.Zpydoc.egg-info/requires.txt
Products.Zpydoc.egg-info/top_level.txt
Products/Zpydoc/ChangeLog
Products/Zpydoc/LICENCE.txt
Products/Zpydoc/MANIFEST
Products/Zpydoc/Permissions.py
Products/Zpydoc/README.txt
Products/Zpydoc/TODO
Products/Zpydoc/ZpyDocumentable.py
Products/Zpydoc/Zpydoc.py
Products/Zpydoc/ZpydocRenderer.py
Products/Zpydoc/__init__.py
Products/Zpydoc/config.py
Products/Zpydoc/configure.zcml
Products/Zpydoc/refresh.txt
Products/Zpydoc/utils.py
Products/Zpydoc/version.txt
Products/Zpydoc/Extensions/Install.py
Products/Zpydoc/Extensions/__init__.py
Products/Zpydoc/browser/__init__.py
Products/Zpydoc/browser/configure.zcml
Products/Zpydoc/browser/portlets/__init__.py
Products/Zpydoc/browser/portlets/configure.zcml
Products/Zpydoc/browser/portlets/zpydoc.pt
Products/Zpydoc/browser/portlets/zpydoc.py
Products/Zpydoc/help/permissions.stx
Products/Zpydoc/help/pydoc.stx
Products/Zpydoc/help/zpydocumentable.stx
Products/Zpydoc/help/zpydocumentable_pkgs.stx
Products/Zpydoc/help/zpydocumentable_props.stx
Products/Zpydoc/inspectors/PythonInfo.py
Products/Zpydoc/inspectors/ZopeInfo.py
Products/Zpydoc/inspectors/__init__.py
Products/Zpydoc/interfaces/IRenderer.py
Products/Zpydoc/interfaces/__init__.py
Products/Zpydoc/profiles/default/metadata.xml
Products/Zpydoc/profiles/default/portlets.xml
Products/Zpydoc/profiles/default/skins.xml
Products/Zpydoc/profiles/default/types.xml
Products/Zpydoc/profiles/default/workflows.xml
Products/Zpydoc/profiles/default/types/Zpydoc.xml
Products/Zpydoc/profiles/default/types/ZpydocPage.xml
Products/Zpydoc/renderers/PyDoc.py
Products/Zpydoc/renderers/Python.py
Products/Zpydoc/renderers/Zope.py
Products/Zpydoc/renderers/__init__.py
Products/Zpydoc/renderers/help/zope.stx
Products/Zpydoc/renderers/zpt/p_document.zpt
Products/Zpydoc/renderers/zpt/p_index.zpt
Products/Zpydoc/renderers/zpt/standard_template.zpt
Products/Zpydoc/renderers/zpt/stylesheet.css
Products/Zpydoc/renderers/zpt/z_document.zpt
Products/Zpydoc/skins/zpydoc/class.png
