Metadata-Version: 1.0
Name: Products.Zpydoc
Version: 4.0.1
Summary: Zope/Plone skins to generate and display docstrings
Home-page: http://www.last-bastion.net/forge/Zpydoc
Author: Alan Milligan
Author-email: alan.milligan@last-bastion.net
License: GPL
Keywords: Zpydoc pydoc
Platform: UNKNOWN
Classifier: Framework :: Plone
Classifier: Programming Language :: Python
Classifier: Development Status :: 5 - Production/Stable
Classifier: License :: OSI Approved :: GNU General Public License (GPL)
